ipython_secrets.py
ipython_secrets-1.1.1.dist-info/LICENSE
ipython_secrets-1.1.1.dist-info/WHEEL
ipython_secrets-1.1.1.dist-info/METADATA
ipython_secrets-1.1.1.dist-info/RECORD
