Metadata-Version: 2.1
Name: ipython-secrets
Version: 1.1.1
Summary: This package provides functions for using secrets in a Jupyter notebook.
Home-page: https://github.com/osteele/ipython-secrets
License: UNKNOWN
Author: Oliver Steele
Author-email: steele@osteele.com
Requires-Python: >=3.5
Classifier: Framework :: IPython
Classifier: Framework :: Jupyter
Classifier: Intended Audience :: Developers
Classifier: License :: OSI Approved :: MIT License
Classifier: Operating System :: OS Independent
Classifier: Programming Language :: Python :: 3.6
Classifier: Programming Language :: Python
Requires-Dist: keyring
Requires-Dist: ipython
Project-URL: Documentation, https://ipython-secrets.readthedocs.io/en/latest/
